shangshanAI/__init__.py
shangshanAI/__version__.py
shangshanAI/_client.py
shangshanAI/utils.py
shangshanAI/api_resource/__init__.py
shangshanAI/api_resource/batches.py
shangshanAI/api_resource/embeddings.py
shangshanAI/api_resource/files.py
shangshanAI/api_resource/images.py
shangshanAI/api_resource/assistant/__init__.py
shangshanAI/api_resource/assistant/assistant.py
shangshanAI/api_resource/chat/__init__.py
shangshanAI/api_resource/chat/async_completions.py
shangshanAI/api_resource/chat/chat.py
shangshanAI/api_resource/chat/completions.py
shangshanAI/api_resource/fine_tuning/__init__.py
shangshanAI/api_resource/fine_tuning/fine_tuning.py
shangshanAI/api_resource/fine_tuning/jobs/__init__.py
shangshanAI/api_resource/fine_tuning/jobs/jobs.py
shangshanAI/api_resource/fine_tuning/models/__init__.py
shangshanAI/api_resource/fine_tuning/models/fine_tuned_models.py
shangshanAI/api_resource/knowledge/__init__.py
shangshanAI/api_resource/knowledge/knowledge.py
shangshanAI/api_resource/knowledge/document/__init__.py
shangshanAI/api_resource/knowledge/document/document.py
shangshanAI/api_resource/tools/__init__.py
shangshanAI/api_resource/tools/tools.py
shangshanAI/api_resource/videos/__init__.py
shangshanAI/api_resource/videos/videos.py
shangshanAI/core/__init__.py
shangshanAI/core/_base_api.py
shangshanAI/core/_base_compat.py
shangshanAI/core/_base_models.py
shangshanAI/core/_base_type.py
shangshanAI/core/_constants.py
shangshanAI/core/_errors.py
shangshanAI/core/_files.py
shangshanAI/core/_http_client.py
shangshanAI/core/_jwt_token.py
shangshanAI/core/_legacy_binary_response.py
shangshanAI/core/_legacy_response.py
shangshanAI/core/_request_opt.py
shangshanAI/core/_response.py
shangshanAI/core/_sse_client.py
shangshanAI/core/logs.py
shangshanAI/core/pagination.py
shangshanAI/core/_utils/__init__.py
shangshanAI/core/_utils/_transform.py
shangshanAI/core/_utils/_typing.py
shangshanAI/core/_utils/_utils.py
shangshanAI/modelscope/__init__.py
shangshanai-0.1.22.dist-info/licenses/LICENSE
shangshanai-0.1.22.dist-info/METADATA
shangshanai-0.1.22.dist-info/WHEEL
shangshanai-0.1.22.dist-info/entry_points.txt
shangshanai-0.1.22.dist-info/top_level.txt
shangshanai-0.1.22.dist-info/RECORD
