Metadata-Version: 2.4
Name: shangshanAI
Version: 0.1.22
Summary: 一个用于从GitLab下载和处理模型的Python SDK
Home-page: https://github.com/你的用户名/shangshanAI
Author: tonysu
Author-email: suguta55@gmail.com
Project-URL: Bug Tracker, https://github.com/你的用户名/shangshanAI/issues
Project-URL: Documentation, https://github.com/你的用户名/shangshanAI#readme
Project-URL: Source Code, https://github.com/你的用户名/shangshanAI
Classifier: Development Status :: 3 - Alpha
Classifier: Intended Audience :: Developers
Classifier: Programming Language :: Python :: 3
Classifier: Programming Language :: Python :: 3.6
Classifier: Programming Language :: Python :: 3.7
Classifier: Programming Language :: Python :: 3.8
Classifier: Programming Language :: Python :: 3.9
Classifier: License :: OSI Approved :: MIT License
Classifier: Operating System :: OS Independent
Requires-Python: >=3.6
License-File: LICENSE
Requires-Dist: requests>=2.25.0
Requires-Dist: tqdm>=4.65.0
Requires-Dist: PyJWT>=2.0.0
Requires-Dist: httpx>=0.24.0
Requires-Dist: typing-extensions>=4.0.0
Requires-Dist: pydantic>=1.10.0
Requires-Dist: aiohttp>=3.8.0
Requires-Dist: anyio>=3.0.0
Requires-Dist: cachetools>=5.2.0
Dynamic: author
Dynamic: author-email
Dynamic: classifier
Dynamic: description
Dynamic: description-content-type
Dynamic: home-page
Dynamic: license-file
Dynamic: project-url
Dynamic: requires-dist
Dynamic: requires-python
Dynamic: summary
